[
  {"tick": 0, "t": 0.000000, "changes": []},
  {"tick": 1, "t": 0.016667, "changes": [{"node": "Bob", "field": "translation", "value": "0.999998689 -0.00270911399 0"}]},
  {"tick": 2, "t": 0.033333, "changes": [{"node": "Bob", "field": "translation", "value": "0.999977887 -0.00812500156 0"}]},
  {"tick": 3, "t": 0.050000, "changes": [{"node": "Bob", "field": "translation", "value": "0.999896109 -0.0162448715 0"}]},
  {"tick": 4, "t": 0.066667, "changes": [{"node": "Bob", "field": "translation", "value": "0.999689102 -0.027064722 0"}]},
  {"tick": 5, "t": 0.083333, "changes": []},
  {"tick": 6, "t": 0.100000, "changes": [{"node": "Bob", "field": "translation", "value": "0.998531401 -0.0567752644 0"}]},
  {"tick": 7, "t": 0.116667, "changes": [{"node": "Bob", "field": "translation", "value": "0.997342288 -0.0756401047 0"}]},
  {"tick": 8, "t": 0.133333, "changes": [{"node": "Bob", "field": "translation", "value": "0.995552301 -0.0971492901 0"}]},
  {"tick": 9, "t": 0.150000, "changes": []},
  {"tick": 10, "t": 0.166667, "changes": [{"node": "Bob", "field": "translation", "value": "0.992990434 -0.121269174 0"}]},
  {"tick": 11, "t": 0.183333, "changes": [{"node": "Bob", "field": "translation", "value": "0.989466667 -0.147953257 0"}]},
  {"tick": 12, "t": 0.200000, "changes": [{"node": "Bob", "field": "translation", "value": "0.97868669 -0.208745763 0"}]},
  {"tick": 13, "t": 0.216667, "changes": [{"node": "Bob", "field": "translation", "value": "0.970969737 -0.242669597 0"}]},
  {"tick": 14, "t": 0.233333, "changes": [{"node": "Bob", "field": "translation", "value": "0.9613747 -0.278782129 0"}]},
  {"tick": 15, "t": 0.250000, "changes": [{"node": "Bob", "field": "translation", "value": "0.949646771 -0.31692636 0"}]},
  {"tick": 16, "t": 0.266667, "changes": [{"node": "Bob", "field": "translation", "value": "0.935528219 -0.356914133 0"}]},
  {"tick": 17, "t": 0.283333, "changes": [{"node": "Bob", "field": "translation", "value": "0.91876334 -0.398523778 0"}]},
  {"tick": 18, "t": 0.300000, "changes": [{"node": "Bob", "field": "translation", "value": "0.899104118 -0.441498369 0"}]},
  {"tick": 19, "t": 0.316667, "changes": []},
  {"tick": 20, "t": 0.333333, "changes": [{"node": "Bob", "field": "translation", "value": "0.87631613 -0.485544473 0"}]},
  {"tick": 21, "t": 0.350000, "changes": [{"node": "Bob", "field": "translation", "value": "0.850185454 -0.530332327 0"}]},
  {"tick": 22, "t": 0.366667, "changes": [{"node": "Bob", "field": "translation", "value": "0.820525646 -0.575496793 0"}]},
  {"tick": 23, "t": 0.383333, "changes": [{"node": "Bob", "field": "translation", "value": "0.787185013 -0.620639563 0"}]},
  {"tick": 24, "t": 0.400000, "changes": [{"node": "Bob", "field": "translation", "value": "0.709069788 -0.709125876 0"}]},
  {"tick": 25, "t": 0.416667, "changes": [{"node": "Bob", "field": "translation", "value": "0.664227009 -0.751548469 0"}]},
  {"tick": 26, "t": 0.433333, "changes": [{"node": "Bob", "field": "translation", "value": "0.615577996 -0.792122066 0"}]},
  {"tick": 27, "t": 0.450000, "changes": [{"node": "Bob", "field": "translation", "value": "0.563238919 -0.830367506 0"}]},
  {"tick": 28, "t": 0.466667, "changes": [{"node": "Bob", "field": "translation", "value": "0.507391155 -0.86581552 0"}]},
  {"tick": 29, "t": 0.483333, "changes": [{"node": "Bob", "field": "translation", "value": "0.448281676 -0.898017287 0"}]}
]
